pyonion/__init__.py
pyonion/remover.py
pyonion/spark.py
pyonion/utils.py
pyonion/data/demo_data.txt
pyonion-0.0.4.dist-info/LICENSE
pyonion-0.0.4.dist-info/METADATA
pyonion-0.0.4.dist-info/WHEEL
pyonion-0.0.4.dist-info/top_level.txt
pyonion-0.0.4.dist-info/RECORD
