Metadata-Version: 2.1
Name: pyonion
Version: 0.0.4
Summary: A minimal implementation of the ONe Instance ONly algorithm
Home-page: https://github.com/AClibbon/pyonion
Author: KAPUK
Author-email: alex.clibbon@kantar.com
License: UNKNOWN
Platform: UNKNOWN
Classifier: Programming Language :: Python :: 3
Classifier: Development Status :: 3 - Alpha
Classifier: Intended Audience :: Science/Research
Classifier: License :: OSI Approved :: GNU Lesser General Public License v3 (LGPLv3)
Classifier: Topic :: Text Processing :: Linguistic
Requires-Python: >=3.7
Provides-Extra: dev
Requires-Dist: pandas ; extra == 'dev'
Requires-Dist: pytest ; extra == 'dev'
Requires-Dist: ipykernel ; extra == 'dev'
Requires-Dist: setuptools-scm ; extra == 'dev'
Provides-Extra: spark
Requires-Dist: pyspark ; extra == 'spark'
